jupyterlab_unianalytics_telemetry/__init__.py
jupyterlab_unianalytics_telemetry/_version.py
jupyterlab_unianalytics_telemetry/handlers.py
jupyterlab_unianalytics_telemetry/tests/__init__.py
jupyterlab_unianalytics_telemetry/tests/test_handlers.py
jupyterlab_unianalytics_telemetry-4.0.20.data/data/etc/jupyter/jupyter_server_config.d/jupyterlab_unianalytics_telemetry.json
jupyterlab_unianalytics_telemetry-4.0.20.data/data/share/jupyter/labextensions/jupyterlab_unianalytics_telemetry/package.json
jupyterlab_unianalytics_telemetry-4.0.20.data/data/share/jupyter/labextensions/jupyterlab_unianalytics_telemetry/schemas/jupyterlab_unianalytics_telemetry/dialogShownSettings.json
jupyterlab_unianalytics_telemetry-4.0.20.data/data/share/jupyter/labextensions/jupyterlab_unianalytics_telemetry/schemas/jupyterlab_unianalytics_telemetry/endpoint.json
jupyterlab_unianalytics_telemetry-4.0.20.data/data/share/jupyter/labextensions/jupyterlab_unianalytics_telemetry/schemas/jupyterlab_unianalytics_telemetry/package.json.orig
jupyterlab_unianalytics_telemetry-4.0.20.data/data/share/jupyter/labextensions/jupyterlab_unianalytics_telemetry/schemas/jupyterlab_unianalytics_telemetry/settings.json
jupyterlab_unianalytics_telemetry-4.0.20.data/data/share/jupyter/labextensions/jupyterlab_unianalytics_telemetry/static/208.6648f8b83204944da455.js
jupyterlab_unianalytics_telemetry-4.0.20.data/data/share/jupyter/labextensions/jupyterlab_unianalytics_telemetry/static/747.bf93f500a68aea565d7e.js
jupyterlab_unianalytics_telemetry-4.0.20.data/data/share/jupyter/labextensions/jupyterlab_unianalytics_telemetry/static/817.0c3c8de730b13beb3f21.js
jupyterlab_unianalytics_telemetry-4.0.20.data/data/share/jupyter/labextensions/jupyterlab_unianalytics_telemetry/static/remoteEntry.6489a301a8f00340d374.js
jupyterlab_unianalytics_telemetry-4.0.20.data/data/share/jupyter/labextensions/jupyterlab_unianalytics_telemetry/static/style.js
jupyterlab_unianalytics_telemetry-4.0.20.dist-info/METADATA
jupyterlab_unianalytics_telemetry-4.0.20.dist-info/WHEEL
jupyterlab_unianalytics_telemetry-4.0.20.dist-info/licenses/LICENSE
jupyterlab_unianalytics_telemetry-4.0.20.dist-info/RECORD
